camelipsum.py
setup.py
camel_ipsum.egg-info/PKG-INFO
camel_ipsum.egg-info/SOURCES.txt
camel_ipsum.egg-info/dependency_links.txt
camel_ipsum.egg-info/not-zip-safe
camel_ipsum.egg-info/requires.txt
camel_ipsum.egg-info/top_level.txt