Metadata-Version: 1.0
Name: camel-ipsum
Version: 1.0
Summary: camel ipsum generator that runs on bash.
Home-page: https://github.com/camelware/camel-ipsum
Author: Camel Soft
Author-email: kayahalil@gmail.com
License: GPLv3
Platform: UNKNOWN
